{
"list": [{ "pic": "renxiang.jpg" },
{ "pic": "renxiang01.jpg", "word": "梦境华，风吹草" },
{ "pic": "renxiang02.jpg", "word": "梦境华，风吹草" },
{ "pic": "renxiang03.jpg", "word": "梦境华，风吹草" },
{ "pic": "renxiang04.jpg", "word": "梦境华，风吹草" },
{ "pic": "renxiang05.jpg", "word": "梦境华，风吹草" },
{ "pic": "renxiang06.jpg", "word": "梦境华，风吹草" },

{ "pic": "fengguang.jpg" },
{ "pic": "fengguang01.jpg", "word": "梦境华，风吹草" },
{ "pic": "fengguang02.jpg", "word": "梦境华，风吹草" },
{ "pic": "fengguang03.jpg", "word": "梦境华，风吹草" },
{ "pic": "fengguang04.jpg", "word": "梦境华，风吹草" },
{ "pic": "fengguang05.jpg", "word": "梦境华，风吹草" },
{ "pic": "fengguang06.jpg", "word": "梦境华，风吹草" },

{ "pic": "renwen.jpg" },
{ "pic": "renwen01.jpg", "word": "梦境华，风吹草" },
{ "pic": "renwen02.jpg", "word": "梦境华，风吹草" },
{ "pic": "renwen03.jpg", "word": "梦境华，风吹草" },
{ "pic": "renwen04.jpg", "word": "梦境华，风吹草" },
{ "pic": "renwen05.jpg", "word": "梦境华，风吹草" },
{ "pic": "renwen06.jpg", "word": "梦境华，风吹草" },

{ "pic": "shengtai.jpg" },
{ "pic": "shengtai01.jpg", "word": "梦境华，风吹草" },
{ "pic": "shengtai02.jpg", "word": "梦境华，风吹草" },
{ "pic": "shengtai03.jpg", "word": "梦境华，风吹草" },
{ "pic": "shengtai04.jpg", "word": "梦境华，风吹草" },
{ "pic": "shengtai05.jpg", "word": "梦境华，风吹草" },
{ "pic": "shengtai06.jpg", "word": "梦境华，风吹草" },

{ "pic": "qita.jpg" },
{ "pic": "qita01.jpg", "word": "梦境华，风吹草" },
{ "pic": "qita02.jpg", "word": "梦境华，风吹草" },
{ "pic": "qita03.jpg", "word": "梦境华，风吹草" },
{ "pic": "qita04.jpg", "word": "梦境华，风吹草" },
{ "pic": "qita05.jpg", "word": "梦境华，风吹草" },
{ "pic": "qita06.jpg", "word": "梦境华，风吹草" },

{ "pic": "more.jpg" }]
}